Gaiatri/Carto.py
Gaiatri/Graph.py
Gaiatri/Load.py
Gaiatri/Query.py
Gaiatri/__init__.py
Gaiatri-0.0.9.dist-info/METADATA
Gaiatri-0.0.9.dist-info/WHEEL
Gaiatri-0.0.9.dist-info/top_level.txt
Gaiatri-0.0.9.dist-info/RECORD
