Metadata-Version: 2.1
Name: Gaiatri
Version: 0.0.9
Summary: Ultra high-level Python library for processing and analysing geo-data.
Home-page: UNKNOWN
Author: MotherBunker (A.N.A. Martam)
Author-email: <motherrrcorp@gmail.com>
License: UNKNOWN
Keywords: python,geospatial,geographical information systems,telemetry
Platform: UNKNOWN
Classifier: Development Status :: 2 - Pre-Alpha
Classifier: Intended Audience :: End Users/Desktop
Classifier: Programming Language :: Python :: 3
Classifier: Operating System :: Unix
Classifier: Operating System :: MacOS :: MacOS X
Classifier: Operating System :: Microsoft :: Windows
Requires-Dist: pandas
Requires-Dist: matplotlib
Requires-Dist: numpy
Requires-Dist: ipyleaflet
